arc/__init__.py
arc/agent.py
arc/agents.py
arc/consts.py
arc/data.py
arc/data_model.py
arc/evaluation.py
arc/launch.py
arc/plot.py
arc/read.py
arc/types.py
arc/version.py
arc/original/ARC/data/evaluation/00576224.json
arc/original/ARC/data/evaluation/009d5c81.json
arc/original/ARC/data/evaluation/00dbd492.json
arc/original/ARC/data/evaluation/03560426.json
arc/original/ARC/data/evaluation/05a7bcf2.json
arc/original/ARC/data/evaluation/0607ce86.json
arc/original/ARC/data/evaluation/0692e18c.json
arc/original/ARC/data/evaluation/070dd51e.json
arc/original/ARC/data/evaluation/08573cc6.json
arc/original/ARC/data/evaluation/0934a4d8.json
arc/original/ARC/data/evaluation/09c534e7.json
arc/original/ARC/data/evaluation/0a1d4ef5.json
arc/original/ARC/data/evaluation/0a2355a6.json
arc/original/ARC/data/evaluation/0b17323b.json
arc/original/ARC/data/evaluation/0bb8deee.json
arc/original/ARC/data/evaluation/0becf7df.json
arc/original/ARC/data/evaluation/0c786b71.json
arc/original/ARC/data/evaluation/0c9aba6e.json
arc/original/ARC/data/evaluation/0d87d2a6.json
arc/original/ARC/data/evaluation/0e671a1a.json
arc/original/ARC/data/evaluation/0f63c0b9.json
arc/original/ARC/data/evaluation/103eff5b.json
arc/original/ARC/data/evaluation/11e1fe23.json
arc/original/ARC/data/evaluation/12422b43.json
arc/original/ARC/data/evaluation/12997ef3.json
arc/original/ARC/data/evaluation/12eac192.json
arc/original/ARC/data/evaluation/136b0064.json
arc/original/ARC/data/evaluation/13713586.json
arc/original/ARC/data/evaluation/137f0df0.json
arc/original/ARC/data/evaluation/140c817e.json
arc/original/ARC/data/evaluation/14754a24.json
arc/original/ARC/data/evaluation/15113be4.json
arc/original/ARC/data/evaluation/15663ba9.json
arc/original/ARC/data/evaluation/15696249.json
arc/original/ARC/data/evaluation/16b78196.json
arc/original/ARC/data/evaluation/17b80ad2.json
arc/original/ARC/data/evaluation/17cae0c1.json
arc/original/ARC/data/evaluation/18419cfa.json
arc_py-0.12.dist-info/LICENSE
arc_py-0.12.dist-info/METADATA
arc_py-0.12.dist-info/WHEEL
arc_py-0.12.dist-info/top_level.txt
arc_py-0.12.dist-info/RECORD
