Metadata-Version: 2.1
Name: arc-py
Version: 0.12
Summary: Utilities for working with ARC Challenge.
Home-page: https://github.com/ikamensh/arc-py
Author: Ilya Kamenshchikov
License: MIT
Keywords: utility,ARC
Platform: UNKNOWN
Classifier: Programming Language :: Python
Classifier: Programming Language :: Python :: 3
Classifier: Programming Language :: Python :: 3.6
Classifier: Programming Language :: Python :: 3.7
Classifier: Programming Language :: Python :: 3.8
Classifier: Programming Language :: Python :: 3.9
Classifier: Topic :: Software Development :: Libraries :: Python Modules
Classifier: Topic :: Utilities
Requires-Python: >=3.6
Requires-Dist: numpy
Requires-Dist: matplotlib
Requires-Dist: appdirs
